{
    "Alberschwende, Vorarlberg, AT": {
        "bbox": {
            "northeast": [
                47.48842000000006,
                9.869230000000062
            ],
            "southwest": [
                47.41242000000007,
                9.793230000000062
            ]
        },
        "count": 13,
        "lat": 47.450420000000065,
        "lon": 9.831230000000062
    },
    "Altach, Vorarlberg, AT": {
        "bbox": {
            "northeast": [
                47.37268000000005,
                9.670180000000068
            ],
            "southwest": [
                47.334680000000056,
                9.632180000000067
            ]
        },
        "count": 5,
        "lat": 47.353680000000054,
        "lon": 9.651180000000068
    },
    "Andelsbuch, Vorarlberg, AT": {
        "bbox": {
            "northeast": [
                47.45642000000003,
                9.938170000000063
            ],
            "southwest": [
                47.37042000000003,
                9.852170000000065
            ]
        },
        "count": 14,
        "lat": 47.41342000000003,
        "lon": 9.895170000000064
    },
    "Au, Vorarlberg, AT": {
        "bbox": {
            "northeast": [
                47.37796000000008,
                10.03695000000004
            ],
            "southwest": [
                47.26796000000008,
                9.92695000000004
            ]
        },
        "count": 14,
        "lat": 47.32296000000008,
        "lon": 9.98195000000004
    },
    "Bartholom\u00c3\u00a4berg, Vorarlberg, AT": {
        "bbox": {
            "northeast": [
                47.09269123238481,
                9.909720458453569
            ],
            "southwest": [
                47.09069123238481,
                9.90772045845357
            ]
        },
        "count": 18,
        "lat": 47.09169123238481,
        "lon": 9.908720458453569
    },
    "Bezau, Vorarlberg, AT": {
        "bbox": {
            "northeast": [
                47.45635000000007,
                9.97329000000005
            ],
            "southwest": [
                47.314350000000076,
                9.83129000000005
            ]
        },
        "count": 11,
        "lat": 47.385350000000074,
        "lon": 9.90229000000005
    },
    "Bildstein, Vorarlberg, AT": {
        "bbox": {
            "northeast": [
                47.530000000000044,
                9.846670000000033
            ],
            "southwest": [
                47.37000000000005,
                9.686670000000033
            ]
        },
        "count": 15,
        "lat": 47.450000000000045,
        "lon": 9.766670000000033
    },
    "Bizau, Vorarlberg, AT": {
        "bbox": {
            "northeast": [
                47.41115000000005,
                9.97166000000007
            ],
            "southwest": [
                47.327150000000046,
                9.88766000000007
            ]
        },
        "count": 7,
        "lat": 47.36915000000005,
        "lon": 9.92966000000007
    },
    "Blons, Vorarlberg, AT": {
        "bbox": {
            "northeast": [
                47.25130000000005,
                9.862140000000048
            ],
            "southwest": [
                47.19530000000005,
                9.806140000000047
            ]
        },
        "count": 4,
        "lat": 47.22330000000005,
        "lon": 9.834140000000048
    },
    "Bludenz, Vorarlberg, AT": {
        "bbox": {
            "northeast": [
                47.36965013000003,
                10.208721221000022
            ],
            "southwest": [
                46.835650130000026,
                9.674721221000024
            ]
        },
        "count": 59,
        "lat": 47.10265013000003,
        "lon": 9.941721221000023
    },
    "Bludesch, Vorarlberg, AT": {
        "bbox": {
            "northeast": [
                47.21788000000008,
                9.761990000000068
            ],
            "southwest": [
                47.17588000000008,
                9.719990000000067
            ]
        },
        "count": 7,
        "lat": 47.19688000000008,
        "lon": 9.740990000000068
    },
    "Brand, Vorarlberg, AT": {
        "bbox": {
            "northeast": [
                47.15434000000006,
                9.788110000000035
            ],
            "southwest": [
                47.06634000000007,
                9.700110000000034
            ]
        },
        "count": 7,
        "lat": 47.110340000000065,
        "lon": 9.744110000000035
    },
    "Bregenz, Vorarlberg, AT": {
        "bbox": {
            "northeast": [
                47.55179000000004,
                9.791670000000066
            ],
            "southwest": [
                47.455790000000036,
                9.695670000000066
            ]
        },
        "count": 189,
        "lat": 47.50379000000004,
        "lon": 9.743670000000066
    },
    "Buch, Vorarlberg, AT": {
        "bbox": {
            "northeast": [
                47.50120000000003,
                9.841550000000035
            ],
            "southwest": [
                47.463200000000036,
                9.803550000000035
            ]
        },
        "count": 3,
        "lat": 47.482200000000034,
        "lon": 9.822550000000035
    },
    "B\u00c3\u00bcrs, Vorarlberg, AT": {
        "bbox": {
            "northeast": [
                47.601079113000075,
                10.264187771000072
            ],
            "southwest": [
                46.87107911300007,
                9.534187771000072
            ]
        },
        "count": 9,
        "lat": 47.23607911300007,
        "lon": 9.899187771000072
    },
    "B\u00c3\u00bcrserberg, Vorarlberg, AT": {
        "bbox": {
            "northeast": [
                47.601079113000075,
                10.264187771000072
            ],
            "southwest": [
                46.87107911300007,
                9.534187771000072
            ]
        },
        "count": 3,
        "lat": 47.23607911300007,
        "lon": 9.899187771000072
    },
    "Dalaas, Vorarlberg, AT": {
        "bbox": {
            "northeast": [
                47.19686000000006,
                10.075030000000071
            ],
            "southwest": [
                47.04886000000006,
                9.927030000000071
            ]
        },
        "count": 13,
        "lat": 47.12286000000006,
        "lon": 10.001030000000071
    },
    "Dam\u00c3\u00bcls, Vorarlberg, AT": {
        "bbox": {
            "northeast": [
                47.601079113000075,
                10.264187771000072
            ],
            "southwest": [
                46.87107911300007,
                9.534187771000072
            ]
        },
        "count": 4,
        "lat": 47.23607911300007,
        "lon": 9.899187771000072
    },
    "Doren, Vorarlberg, AT": {
        "bbox": {
            "northeast": [
                47.52275000000006,
                9.91104000000004
            ],
            "southwest": [
                47.46275000000006,
                9.851040000000042
            ]
        },
        "count": 3,
        "lat": 47.49275000000006,
        "lon": 9.881040000000041
    },
    "Dornbirn, Vorarlberg, AT": {
        "bbox": {
            "northeast": [
                47.49319000000004,
                9.823780000000072
            ],
            "southwest": [
                47.333190000000045,
                9.663780000000072
            ]
        },
        "count": 103,
        "lat": 47.41319000000004,
        "lon": 9.743780000000072
    },
    "D\u00c3\u00bcns, Vorarlberg, AT": {
        "bbox": {
            "northeast": [
                47.601079113000075,
                10.264187771000072
            ],
            "southwest": [
                46.87107911300007,
                9.534187771000072
            ]
        },
        "count": 5,
        "lat": 47.23607911300007,
        "lon": 9.899187771000072
    },
    "D\u00c3\u00bcnserberg, Vorarlberg, AT": {
        "bbox": {
            "northeast": [
                47.601079113000075,
                10.264187771000072
            ],
            "southwest": [
                46.87107911300007,
                9.534187771000072
            ]
        },
        "count": 2,
        "lat": 47.23607911300007,
        "lon": 9.899187771000072
    },
    "Egg, Vorarlberg, AT": {
        "bbox": {
            "northeast": [
                47.52702000000004,
                9.993100000000023
            ],
            "southwest": [
                47.33502000000005,
                9.801100000000023
            ]
        },
        "count": 18,
        "lat": 47.431020000000046,
        "lon": 9.897100000000023
    },
    "Eichenberg, Vorarlberg, AT": {
        "bbox": {
            "northeast": [
                47.56154000000006,
                9.805190000000062
            ],
            "southwest": [
                47.51154000000006,
                9.755190000000061
            ]
        },
        "count": 3,
        "lat": 47.53654000000006,
        "lon": 9.780190000000061
    },
    "Feldkirch, Vorarlberg, AT": {
        "bbox": {
            "northeast": [
                47.28714000000004,
                9.645740000000067
            ],
            "southwest": [
                47.189140000000044,
                9.547740000000069
            ]
        },
        "count": 299,
        "lat": 47.238140000000044,
        "lon": 9.596740000000068
    },
    "Fontanella, Vorarlberg, AT": {
        "bbox": {
            "northeast": [
                47.292660000000055,
                9.955060000000044
            ],
            "southwest": [
                47.20266000000005,
                9.865060000000044
            ]
        },
        "count": 5,
        "lat": 47.24766000000005,
        "lon": 9.910060000000044
    },
    "Frastanz, Vorarlberg, AT": {
        "bbox": {
            "northeast": [
                47.26296000000003,
                9.675930000000058
            ],
            "southwest": [
                47.17096000000003,
                9.58393000000006
            ]
        },
        "count": 16,
        "lat": 47.21696000000003,
        "lon": 9.629930000000058
    },
    "Fraxern, Vorarlberg, AT": {
        "bbox": {
            "northeast": [
                47.34166000000006,
                9.701950000000023
            ],
            "southwest": [
                47.28766000000006,
                9.647950000000025
            ]
        },
        "count": 5,
        "lat": 47.31466000000006,
        "lon": 9.674950000000024
    },
    "Fu\u00c3\u0178ach, Vorarlberg, AT": {
        "bbox": {
            "northeast": [
                47.601079113000075,
                10.264187771000072
            ],
            "southwest": [
                46.87107911300007,
                9.534187771000072
            ]
        },
        "count": 4,
        "lat": 47.23607911300007,
        "lon": 9.899187771000072
    },
    "Gai\u00c3\u0178au, Vorarlberg, AT": {
        "bbox": {
            "northeast": [
                47.601079113000075,
                10.264187771000072
            ],
            "southwest": [
                46.87107911300007,
                9.534187771000072
            ]
        },
        "count": 3,
        "lat": 47.23607911300007,
        "lon": 9.899187771000072
    },
    "Gaschurn, Vorarlberg, AT": {
        "bbox": {
            "northeast": [
                47.08494000000007,
                10.12057000000004
            ],
            "southwest": [
                46.892940000000074,
                9.92857000000004
            ]
        },
        "count": 16,
        "lat": 46.98894000000007,
        "lon": 10.02457000000004
    },
    "G\u00c3\u00b6fis, Vorarlberg, AT": {
        "bbox": {
            "northeast": [
                47.601079113000075,
                10.264187771000072
            ],
            "southwest": [
                46.87107911300007,
                9.534187771000072
            ]
        },
        "count": 10,
        "lat": 47.23607911300007,
        "lon": 9.899187771000072
    },
    "G\u00c3\u00b6tzis, Vorarlberg, AT": {
        "bbox": {
            "northeast": [
                47.601079113000075,
                10.264187771000072
            ],
            "southwest": [
                46.87107911300007,
                9.534187771000072
            ]
        },
        "count": 20,
        "lat": 47.23607911300007,
        "lon": 9.899187771000072
    },
    "Hard, Vorarlberg, AT": {
        "bbox": {
            "northeast": [
                47.522100000000066,
                9.723850000000068
            ],
            "southwest": [
                47.45610000000006,
                9.657850000000069
            ]
        },
        "count": 26,
        "lat": 47.489100000000064,
        "lon": 9.690850000000069
    },
    "Hittisau, Vorarlberg, AT": {
        "bbox": {
            "northeast": [
                47.51938000000004,
                10.015690000000037
            ],
            "southwest": [
                47.401380000000046,
                9.897690000000038
            ]
        },
        "count": 15,
        "lat": 47.46038000000004,
        "lon": 9.956690000000037
    },
    "Hohenems, Vorarlberg, AT": {
        "bbox": {
            "northeast": [
                47.404250000000076,
                9.730920000000053
            ],
            "southwest": [
                47.32025000000007,
                9.646920000000053
            ]
        },
        "count": 102,
        "lat": 47.362250000000074,
        "lon": 9.688920000000053
    },
    "Hohenweiler, Vorarlberg, AT": {
        "bbox": {
            "northeast": [
                47.613670000000035,
                9.806340000000057
            ],
            "southwest": [
                47.56367000000004,
                9.756340000000057
            ]
        },
        "count": 8,
        "lat": 47.588670000000036,
        "lon": 9.781340000000057
    },
    "H\u00c3\u00b6chst, Vorarlberg, AT": {
        "bbox": {
            "northeast": [
                47.601079113000075,
                10.264187771000072
            ],
            "southwest": [
                46.87107911300007,
                9.534187771000072
            ]
        },
        "count": 7,
        "lat": 47.23607911300007,
        "lon": 9.899187771000072
    },
    "H\u00c3\u00b6rbranz, Vorarlberg, AT": {
        "bbox": {
            "northeast": [
                47.57882000000004,
                9.776330000000062
            ],
            "southwest": [
                47.53282000000004,
                9.730330000000063
            ]
        },
        "count": 9,
        "lat": 47.55582000000004,
        "lon": 9.753330000000062
    },
    "Innerbraz, Vorarlberg, AT": {
        "bbox": {
            "northeast": [
                47.175760000000075,
                9.94857000000007
            ],
            "southwest": [
                47.11376000000008,
                9.886570000000068
            ]
        },
        "count": 10,
        "lat": 47.144760000000076,
        "lon": 9.917570000000069
    },
    "Kennelbach, Vorarlberg, AT": {
        "bbox": {
            "northeast": [
                47.49866000000008,
                9.785280000000052
            ],
            "southwest": [
                47.46066000000008,
                9.747280000000051
            ]
        },
        "count": 8,
        "lat": 47.47966000000008,
        "lon": 9.766280000000052
    },
    "Klaus, Vorarlberg, AT": {
        "bbox": {
            "northeast": [
                47.32894000000007,
                9.666580000000028
            ],
            "southwest": [
                47.28894000000006,
                9.626580000000029
            ]
        },
        "count": 3,
        "lat": 47.308940000000064,
        "lon": 9.646580000000029
    },
    "Kl\u00c3\u00b6sterle, Vorarlberg, AT": {
        "bbox": {
            "northeast": [
                47.131077701333524,
                10.10030881277554
            ],
            "southwest": [
                47.12907770133353,
                10.09830881277554
            ]
        },
        "count": 8,
        "lat": 47.130077701333526,
        "lon": 10.09930881277554
    },
    "Koblach, Vorarlberg, AT": {
        "bbox": {
            "northeast": [
                47.35362000000007,
                9.625280000000064
            ],
            "southwest": [
                47.307620000000064,
                9.579280000000065
            ]
        },
        "count": 4,
        "lat": 47.33062000000007,
        "lon": 9.602280000000064
    },
    "Krumbach, Vorarlberg, AT": {
        "bbox": {
            "northeast": [
                47.50947000000008,
                9.957890000000075
            ],
            "southwest": [
                47.46147000000008,
                9.909890000000077
            ]
        },
        "count": 5,
        "lat": 47.48547000000008,
        "lon": 9.933890000000076
    },
    "Langen bei Bregenz, Vorarlberg, AT": {
        "bbox": {
            "northeast": [
                47.542570000000076,
                9.861970000000051
            ],
            "southwest": [
                47.47457000000008,
                9.79397000000005
            ]
        },
        "count": 4,
        "lat": 47.50857000000008,
        "lon": 9.82797000000005
    },
    "Langenegg, Vorarlberg, AT": {
        "bbox": {
            "northeast": [
                47.49608000000004,
                9.92494000000003
            ],
            "southwest": [
                47.440080000000044,
                9.868940000000029
            ]
        },
        "count": 7,
        "lat": 47.46808000000004,
        "lon": 9.89694000000003
    },
    "Laterns, Vorarlberg, AT": {
        "bbox": {
            "northeast": [
                47.32517000000004,
                9.761800000000024
            ],
            "southwest": [
                47.20717000000005,
                9.643800000000025
            ]
        },
        "count": 9,
        "lat": 47.266170000000045,
        "lon": 9.702800000000025
    },
    "Lauterach, Vorarlberg, AT": {
        "bbox": {
            "northeast": [
                47.50329000000004,
                9.757480000000033
            ],
            "southwest": [
                47.451290000000036,
                9.705480000000033
            ]
        },
        "count": 10,
        "lat": 47.47729000000004,
        "lon": 9.731480000000033
    },
    "Lech, Vorarlberg, AT": {
        "bbox": {
            "northeast": [
                47.27929000000003,
                10.212770000000065
            ],
            "southwest": [
                47.137290000000036,
                10.070770000000065
            ]
        },
        "count": 20,
        "lat": 47.208290000000034,
        "lon": 10.141770000000065
    },
    "Lingenau, Vorarlberg, AT": {
        "bbox": {
            "northeast": [
                47.471230000000034,
                9.94113000000003
            ],
            "southwest": [
                47.42923000000003,
                9.899130000000028
            ]
        },
        "count": 6,
        "lat": 47.45023000000003,
        "lon": 9.920130000000029
    },
    "Lochau, Vorarlberg, AT": {
        "bbox": {
            "northeast": [
                47.55693000000004,
                9.777820000000032
            ],
            "southwest": [
                47.502930000000035,
                9.723820000000034
            ]
        },
        "count": 14,
        "lat": 47.529930000000036,
        "lon": 9.750820000000033
    },
    "Lor\u00c3\u00bcns, Vorarlberg, AT": {
        "bbox": {
            "northeast": [
                47.601079113000075,
                10.264187771000072
            ],
            "southwest": [
                46.87107911300007,
                9.534187771000072
            ]
        },
        "count": 3,
        "lat": 47.23607911300007,
        "lon": 9.899187771000072
    },
    "Ludesch, Vorarlberg, AT": {
        "bbox": {
            "northeast": [
                47.22107000000003,
                9.811260000000042
            ],
            "southwest": [
                47.165070000000036,
                9.75526000000004
            ]
        },
        "count": 6,
        "lat": 47.193070000000034,
        "lon": 9.783260000000041
    },
    "Lustenau, Vorarlberg, AT": {
        "bbox": {
            "northeast": [
                47.45832000000003,
                9.690650000000023
            ],
            "southwest": [
                47.394320000000036,
                9.626650000000023
            ]
        },
        "count": 22,
        "lat": 47.42632000000003,
        "lon": 9.658650000000023
    },
    "Meiningen, Vorarlberg, AT": {
        "bbox": {
            "northeast": [
                47.31733000000008,
                9.597710000000058
            ],
            "southwest": [
                47.27933000000008,
                9.559710000000058
            ]
        },
        "count": 6,
        "lat": 47.29833000000008,
        "lon": 9.578710000000058
    },
    "Mellau, Vorarlberg, AT": {
        "bbox": {
            "northeast": [
                47.39824000000007,
                9.929200000000069
            ],
            "southwest": [
                47.30424000000008,
                9.835200000000068
            ]
        },
        "count": 7,
        "lat": 47.351240000000075,
        "lon": 9.882200000000068
    },
    "Mittelberg, Vorarlberg, AT": {
        "bbox": {
            "northeast": [
                47.39594000000005,
                10.22683000000006
            ],
            "southwest": [
                47.25194000000005,
                10.082830000000062
            ]
        },
        "count": 28,
        "lat": 47.32394000000005,
        "lon": 10.15483000000006
    },
    "M\u00c3\u00a4der, Vorarlberg, AT": {
        "bbox": {
            "northeast": [
                47.46583900000002,
                9.675331750000003
            ],
            "southwest": [
                47.46383900000002,
                9.673331750000004
            ]
        },
        "count": 5,
        "lat": 47.46483900000002,
        "lon": 9.674331750000004
    },
    "M\u00c3\u00b6ggers, Vorarlberg, AT": {
        "bbox": {
            "northeast": [
                47.601079113000075,
                10.264187771000072
            ],
            "southwest": [
                46.87107911300007,
                9.534187771000072
            ]
        },
        "count": 3,
        "lat": 47.23607911300007,
        "lon": 9.899187771000072
    },
    "Nenzing, Vorarlberg, AT": {
        "bbox": {
            "northeast": [
                47.26422000000007,
                9.783820000000041
            ],
            "southwest": [
                47.10622000000007,
                9.62582000000004
            ]
        },
        "count": 30,
        "lat": 47.18522000000007,
        "lon": 9.70482000000004
    },
    "N\u00c3\u00bcziders, Vorarlberg, AT": {
        "bbox": {
            "northeast": [
                47.601079113000075,
                10.264187771000072
            ],
            "southwest": [
                46.87107911300007,
                9.534187771000072
            ]
        },
        "count": 7,
        "lat": 47.23607911300007,
        "lon": 9.899187771000072
    },
    "Raggal, Vorarlberg, AT": {
        "bbox": {
            "northeast": [
                47.27078000000003,
                9.89390000000006
            ],
            "southwest": [
                47.152780000000035,
                9.775900000000062
            ]
        },
        "count": 8,
        "lat": 47.21178000000003,
        "lon": 9.834900000000061
    },
    "Rankweil, Vorarlberg, AT": {
        "bbox": {
            "northeast": [
                47.31419000000004,
                9.688070000000023
            ],
            "southwest": [
                47.224190000000036,
                9.598070000000023
            ]
        },
        "count": 32,
        "lat": 47.26919000000004,
        "lon": 9.643070000000023
    },
    "Reuthe, Vorarlberg, AT": {
        "bbox": {
            "northeast": [
                47.39799000000004,
                9.924480000000063
            ],
            "southwest": [
                47.345990000000036,
                9.872480000000063
            ]
        },
        "count": 4,
        "lat": 47.37199000000004,
        "lon": 9.898480000000063
    },
    "Riefensberg, Vorarlberg, AT": {
        "bbox": {
            "northeast": [
                47.535950000000064,
                9.995150000000075
            ],
            "southwest": [
                47.473950000000066,
                9.933150000000074
            ]
        },
        "count": 3,
        "lat": 47.504950000000065,
        "lon": 9.964150000000075
    },
    "R\u00c3\u00b6ns, Vorarlberg, AT": {
        "bbox": {
            "northeast": [
                47.601079113000075,
                10.264187771000072
            ],
            "southwest": [
                46.87107911300007,
                9.534187771000072
            ]
        },
        "count": 1,
        "lat": 47.23607911300007,
        "lon": 9.899187771000072
    },
    "R\u00c3\u00b6this, Vorarlberg, AT": {
        "bbox": {
            "northeast": [
                47.601079113000075,
                10.264187771000072
            ],
            "southwest": [
                46.87107911300007,
                9.534187771000072
            ]
        },
        "count": 8,
        "lat": 47.23607911300007,
        "lon": 9.899187771000072
    },
    "Sankt Anton im Montafon, Vorarlberg, AT": {
        "bbox": {
            "northeast": [
                47.12868000000007,
                9.88092000000004
            ],
            "southwest": [
                47.09668000000007,
                9.84892000000004
            ]
        },
        "count": 1,
        "lat": 47.11268000000007,
        "lon": 9.86492000000004
    },
    "Sankt Gallenkirch, Vorarlberg, AT": {
        "bbox": {
            "northeast": [
                47.10956000000006,
                10.056160000000045
            ],
            "southwest": [
                46.93556000000005,
                9.882160000000045
            ]
        },
        "count": 19,
        "lat": 47.022560000000055,
        "lon": 9.969160000000045
    },
    "Sankt Gerold, Vorarlberg, AT": {
        "bbox": {
            "northeast": [
                47.24561000000008,
                9.84130000000007
            ],
            "southwest": [
                47.19561000000008,
                9.791300000000069
            ]
        },
        "count": 2,
        "lat": 47.22061000000008,
        "lon": 9.81630000000007
    },
    "Satteins, Vorarlberg, AT": {
        "bbox": {
            "northeast": [
                47.253140000000066,
                9.698390000000055
            ],
            "southwest": [
                47.19714000000007,
                9.642390000000054
            ]
        },
        "count": 8,
        "lat": 47.22514000000007,
        "lon": 9.670390000000054
    },
    "Schlins, Vorarlberg, AT": {
        "bbox": {
            "northeast": [
                47.222440000000084,
                9.71405000000006
            ],
            "southwest": [
                47.18244000000008,
                9.674050000000062
            ]
        },
        "count": 7,
        "lat": 47.20244000000008,
        "lon": 9.694050000000061
    },
    "Schnepfau, Vorarlberg, AT": {
        "bbox": {
            "northeast": [
                47.38721000000007,
                9.980520000000045
            ],
            "southwest": [
                47.317210000000074,
                9.910520000000044
            ]
        },
        "count": 7,
        "lat": 47.35221000000007,
        "lon": 9.945520000000045
    },
    "Schnifis, Vorarlberg, AT": {
        "bbox": {
            "northeast": [
                47.23516000000005,
                9.750250000000037
            ],
            "southwest": [
                47.19316000000005,
                9.708250000000035
            ]
        },
        "count": 3,
        "lat": 47.21416000000005,
        "lon": 9.729250000000036
    },
    "Schoppernau, Vorarlberg, AT": {
        "bbox": {
            "northeast": [
                47.36003000000005,
                10.065790000000048
            ],
            "southwest": [
                47.26403000000005,
                9.969790000000048
            ]
        },
        "count": 11,
        "lat": 47.31203000000005,
        "lon": 10.017790000000048
    },
    "Schruns, Vorarlberg, AT": {
        "bbox": {
            "northeast": [
                47.11797000000006,
                9.957720000000041
            ],
            "southwest": [
                47.04197000000006,
                9.88172000000004
            ]
        },
        "count": 23,
        "lat": 47.07997000000006,
        "lon": 9.91972000000004
    },
    "Schr\u00c3\u00b6cken, Vorarlberg, AT": {
        "bbox": {
            "northeast": [
                47.26304241157516,
                10.078524421006287
            ],
            "southwest": [
                47.26104241157516,
                10.076524421006289
            ]
        },
        "count": 4,
        "lat": 47.26204241157516,
        "lon": 10.077524421006288
    },
    "Schwarzach, Vorarlberg, AT": {
        "bbox": {
            "northeast": [
                47.46487000000007,
                9.782520000000028
            ],
            "southwest": [
                47.42687000000007,
                9.744520000000028
            ]
        },
        "count": 4,
        "lat": 47.44587000000007,
        "lon": 9.763520000000028
    },
    "Schwarzenberg, Vorarlberg, AT": {
        "bbox": {
            "northeast": [
                47.450860000000056,
                9.889640000000066
            ],
            "southwest": [
                47.37686000000006,
                9.815640000000064
            ]
        },
        "count": 46,
        "lat": 47.41386000000006,
        "lon": 9.852640000000065
    },
    "Sibratsgf\u00c3\u00a4ll, Vorarlberg, AT": {
        "bbox": {
            "northeast": [
                47.41499101623223,
                10.071108665334398
            ],
            "southwest": [
                47.41299101623223,
                10.069108665334399
            ]
        },
        "count": 2,
        "lat": 47.41399101623223,
        "lon": 10.070108665334399
    },
    "Silbertal, Vorarlberg, AT": {
        "bbox": {
            "northeast": [
                47.16806000000007,
                10.055600000000071
            ],
            "southwest": [
                47.02006000000007,
                9.907600000000071
            ]
        },
        "count": 6,
        "lat": 47.09406000000007,
        "lon": 9.981600000000071
    },
    "Sonntag, Vorarlberg, AT": {
        "bbox": {
            "northeast": [
                47.31472000000004,
                9.980110000000035
            ],
            "southwest": [
                47.16472000000003,
                9.830110000000037
            ]
        },
        "count": 9,
        "lat": 47.239720000000034,
        "lon": 9.905110000000036
    },
    "Stallehr, Vorarlberg, AT": {
        "bbox": {
            "northeast": [
                47.213060000000056,
                9.930000000000023
            ],
            "southwest": [
                47.05306000000006,
                9.770000000000023
            ]
        },
        "count": 2,
        "lat": 47.13306000000006,
        "lon": 9.850000000000023
    },
    "Sulz, Vorarlberg, AT": {
        "bbox": {
            "northeast": [
                47.30478000000006,
                9.670050000000064
            ],
            "southwest": [
                47.27078000000005,
                9.636050000000065
            ]
        },
        "count": 4,
        "lat": 47.287780000000055,
        "lon": 9.653050000000064
    },
    "Sulzberg, Vorarlberg, AT": {
        "bbox": {
            "northeast": [
                47.55990000000004,
                9.950770000000047
            ],
            "southwest": [
                47.48190000000004,
                9.872770000000047
            ]
        },
        "count": 13,
        "lat": 47.52090000000004,
        "lon": 9.911770000000047
    },
    "Th\u00c3\u00bcringen, Vorarlberg, AT": {
        "bbox": {
            "northeast": [
                47.601079113000075,
                10.264187771000072
            ],
            "southwest": [
                46.87107911300007,
                9.534187771000072
            ]
        },
        "count": 9,
        "lat": 47.23607911300007,
        "lon": 9.899187771000072
    },
    "Th\u00c3\u00bcringerberg, Vorarlberg, AT": {
        "bbox": {
            "northeast": [
                47.601079113000075,
                10.264187771000072
            ],
            "southwest": [
                46.87107911300007,
                9.534187771000072
            ]
        },
        "count": 2,
        "lat": 47.23607911300007,
        "lon": 9.899187771000072
    },
    "Tschagguns, Vorarlberg, AT": {
        "bbox": {
            "northeast": [
                47.13773000000003,
                9.961960000000031
            ],
            "southwest": [
                47.01773000000003,
                9.84196000000003
            ]
        },
        "count": 12,
        "lat": 47.07773000000003,
        "lon": 9.901960000000031
    },
    "Vandans, Vorarlberg, AT": {
        "bbox": {
            "northeast": [
                47.162300000000066,
                9.932700000000061
            ],
            "southwest": [
                47.028300000000065,
                9.79870000000006
            ]
        },
        "count": 16,
        "lat": 47.095300000000066,
        "lon": 9.86570000000006
    },
    "Viktorsberg, Vorarlberg, AT": {
        "bbox": {
            "northeast": [
                47.379720000000034,
                9.746670000000067
            ],
            "southwest": [
                47.21972000000004,
                9.586670000000067
            ]
        },
        "count": 3,
        "lat": 47.299720000000036,
        "lon": 9.666670000000067
    },
    "Warth, Vorarlberg, AT": {
        "bbox": {
            "northeast": [
                47.29825000000003,
                10.223040000000061
            ],
            "southwest": [
                47.21825000000003,
                10.143040000000063
            ]
        },
        "count": 3,
        "lat": 47.25825000000003,
        "lon": 10.183040000000062
    },
    "Weiler, Vorarlberg, AT": {
        "bbox": {
            "northeast": [
                47.32255000000003,
                9.671820000000077
            ],
            "southwest": [
                47.28455000000003,
                9.633820000000076
            ]
        },
        "count": 4,
        "lat": 47.30355000000003,
        "lon": 9.652820000000077
    },
    "Wolfurt, Vorarlberg, AT": {
        "bbox": {
            "northeast": [
                47.49714000000003,
                9.780030000000037
            ],
            "southwest": [
                47.43714000000003,
                9.720030000000039
            ]
        },
        "count": 5,
        "lat": 47.46714000000003,
        "lon": 9.750030000000038
    },
    "Zwischenwasser, Vorarlberg, AT": {
        "bbox": {
            "northeast": [
                47.322400000000066,
                9.708810000000021
            ],
            "southwest": [
                47.23640000000007,
                9.622810000000023
            ]
        },
        "count": 13,
        "lat": 47.27940000000007,
        "lon": 9.665810000000022
    },
    "\u00c3\u0153bersaxen, Vorarlberg, AT": {
        "bbox": {
            "northeast": [
                47.601079113000075,
                10.264187771000072
            ],
            "southwest": [
                46.87107911300007,
                9.534187771000072
            ]
        },
        "count": 4,
        "lat": 47.23607911300007,
        "lon": 9.899187771000072
    }
}